{
  "ComponentIndexes": {},
  "ControlUniqueGuids": {},
  "ControlUniqueIds": {
    "Acessivel": 162,
    "AddArquivo": 251,
    "AddMediaButton1": 252,
    "AddPicture1": 153,
    "AddPicture2": 46,
    "ajuda": 245,
    "Ajuda": 187,
    "Ajuda_1": 247,
    "Anexo_DataCard1": 149,
    "Anexo_DataCard2": 42,
    "App": 1,
    "Aumentar fonte": 177,
    "Body3": 236,
    "Body3_1": 207,
    "Button2": 218,
    "color_amarelo": 165,
    "color_branco": 166,
    "color_preto": 167,
    "Configuracao": 186,
    "Container1": 193,
    "Container1_1": 222,
    "Cor_DataCard1": 134,
    "Cor_DataCard2": 48,
    "Cor_DataCard3": 11,
    "Cores": 164,
    "Data_DataCard1": 53,
    "Data_DataCard2": 119,
    "DataCardKey1": 44,
    "DataCardKey10": 106,
    "DataCardKey11": 55,
    "DataCardKey12": 60,
    "DataCardKey13": 101,
    "DataCardKey14": 126,
    "DataCardKey15": 146,
    "DataCardKey16": 65,
    "DataCardKey17": 70,
    "DataCardKey18": 116,
    "DataCardKey19": 111,
    "DataCardKey2": 136,
    "DataCardKey20": 75,
    "DataCardKey21": 80,
    "DataCardKey22": 85,
    "DataCardKey23": 90,
    "DataCardKey24": 33,
    "DataCardKey25": 95,
    "DataCardKey26": 121,
    "DataCardKey27": 23,
    "DataCardKey28": 28,
    "DataCardKey29": 141,
    "DataCardKey3": 131,
    "DataCardKey4": 151,
    "DataCardKey6": 18,
    "DataCardKey7": 50,
    "DataCardKey8": 8,
    "DataCardKey9": 13,
    "DataCardValue1": 51,
    "DataCardValue10": 61,
    "DataCardValue11": 102,
    "DataCardValue12": 127,
    "DataCardValue13": 147,
    "DataCardValue14": 66,
    "DataCardValue15": 71,
    "DataCardValue16": 117,
    "DataCardValue17": 112,
    "DataCardValue18": 76,
    "DataCardValue19": 81,
    "DataCardValue2": 137,
    "DataCardValue20": 86,
    "DataCardValue21": 91,
    "DataCardValue22": 34,
    "DataCardValue23": 96,
    "DataCardValue24": 122,
    "DataCardValue25": 24,
    "DataCardValue26": 29,
    "DataCardValue27": 142,
    "DataCardValue3": 132,
    "DataCardValue5": 19,
    "DataCardValue6": 9,
    "DataCardValue7": 14,
    "DataCardValue8": 56,
    "DataCardValue9": 107,
    "Diâmetro_DataCard2": 16,
    "Diâmetro_DataCard3": 58,
    "Diâmetro_DataCard4": 139,
    "ErrorMessage1": 47,
    "ErrorMessage10": 108,
    "ErrorMessage11": 10,
    "ErrorMessage12": 15,
    "ErrorMessage13": 103,
    "ErrorMessage14": 25,
    "ErrorMessage15": 148,
    "ErrorMessage16": 62,
    "ErrorMessage17": 67,
    "ErrorMessage18": 118,
    "ErrorMessage19": 113,
    "ErrorMessage2": 138,
    "ErrorMessage20": 72,
    "ErrorMessage21": 30,
    "ErrorMessage22": 77,
    "ErrorMessage23": 82,
    "ErrorMessage24": 87,
    "ErrorMessage25": 92,
    "ErrorMessage26": 97,
    "ErrorMessage27": 123,
    "ErrorMessage28": 143,
    "ErrorMessage3": 133,
    "ErrorMessage4": 154,
    "ErrorMessage5": 128,
    "ErrorMessage6": 52,
    "ErrorMessage7": 20,
    "ErrorMessage8": 35,
    "ErrorMessage9": 57,
    "Fabricante_DataCard1": 93,
    "Fabricante_DataCard2": 144,
    "Fabricante_DataCard3": 31,
    "Fechar": 176,
    "Filtro_1": 225,
    "Filtro_2": 196,
    "Fontes": 168,
    "Fontes_1": 173,
    "Fontes_2": 174,
    "Fontes_3": 170,
    "Fontes_4": 175,
    "Form1": 98,
    "Form2": 5,
    "Form3": 41,
    "Gallery2": 231,
    "Gallery2_1": 202,
    "galleryTemplate3": 232,
    "galleryTemplate3_1": 203,
    "Group1": 256,
    "Group10": 243,
    "Group11": 244,
    "Group12": 242,
    "Group2": 178,
    "Group3": 179,
    "Group4": 212,
    "Group5": 190,
    "Group6": 213,
    "Group8": 159,
    "Group9": 160,
    "Host": 3,
    "Icon1": 158,
    "Icon3": 200,
    "Icon3_1": 201,
    "Icon3_2": 228,
    "Icon3_3": 230,
    "Icon4": 241,
    "Icon5": 180,
    "Icon5_1": 188,
    "Icon6": 199,
    "Icon6_1": 229,
    "Icon7": 240,
    "Icon7_1": 157,
    "Icon7_2": 210,
    "Icon7_3": 36,
    "Icon7_4": 254,
    "Image1": 45,
    "Image3": 152,
    "Image5": 215,
    "Label1": 181,
    "Label2_2": 40,
    "Label3": 239,
    "Label3_1": 156,
    "Label3_2": 155,
    "Label3_3": 211,
    "Label3_4": 37,
    "Label3_5": 238,
    "Label3_6": 255,
    "Label4": 172,
    "Label4_1": 169,
    "Localização_DataCard1": 109,
    "Localização_DataCard2": 26,
    "Localização_DataCard3": 68,
    "localizar": 191,
    "Localizar 2": 4,
    "Localizar Button": 184,
    "login": 214,
    "Logo estoque": 183,
    "Logo Estoque": 221,
    "Logo estoque_1": 249,
    "Logo Estoque_1": 192,
    "Logo Estoque_2": 194,
    "Logo Estoque_3": 223,
    "Material_DataCard1": 129,
    "Material_DataCard2": 99,
    "Material_DataCard3": 63,
    "Material_DataCard4": 6,
    "movimentacao": 220,
    "Movimentacao Button": 185,
    "Movimentacao Button_1": 38,
    "movimentacao2": 39,
    "NextArrow5": 234,
    "NextArrow5_1": 205,
    "Nome_DataCard1": 73,
    "Nome_DataCard3": 124,
    "PopUp_acessibilidade": 163,
    "principal": 161,
    "Quant._DataCard1": 21,
    "Quant._DataCard2": 114,
    "Quant._DataCard3": 78,
    "Radio1_2": 226,
    "Radio1_3": 227,
    "Radio1_4": 197,
    "Radio1_5": 198,
    "Separator5_1": 208,
    "Separator5_2": 237,
    "Slider1": 171,
    "StarVisible1": 43,
    "StarVisible10": 105,
    "StarVisible11": 7,
    "StarVisible12": 12,
    "StarVisible13": 100,
    "StarVisible14": 22,
    "StarVisible15": 145,
    "StarVisible16": 59,
    "StarVisible17": 64,
    "StarVisible18": 115,
    "StarVisible19": 110,
    "StarVisible2": 135,
    "StarVisible20": 69,
    "StarVisible21": 27,
    "StarVisible22": 74,
    "StarVisible23": 79,
    "StarVisible24": 84,
    "StarVisible25": 89,
    "StarVisible26": 94,
    "StarVisible27": 120,
    "StarVisible28": 140,
    "StarVisible3": 130,
    "StarVisible4": 150,
    "StarVisible5": 125,
    "StarVisible6": 49,
    "StarVisible7": 17,
    "StarVisible8": 32,
    "StarVisible9": 54,
    "Status_DataCard1": 83,
    "Status_DataCard2": 104,
    "Subtitle5": 235,
    "Subtitle5_1": 206,
    "TextInput1": 217,
    "TextInput2": 216,
    "TextInput3": 250,
    "TextInput3_1": 246,
    "TextSearchBox1_1": 224,
    "TextSearchBox1_2": 195,
    "Timer2": 182,
    "Title5": 233,
    "Title5_1": 204,
    "Título_DataCard1": 88,
    "Tooling Logo": 189,
    "Tooling Logo_1": 219,
    "Tooling Logo_2": 209,
    "Tooling Logo_4": 253,
    "UploadedImage1": 248
  },
  "FunctionParamsInvariantScripts": {},
  "FunctionParamsInvariantScriptsOnInstances": {},
  "HeaderLastSavedDateTimeUTC": "10/02/2023 14:53:02",
  "IsLegacyComponentAllowGlobalScopeCase": false,
  "LocalConnectionIDReferences": {
    "a04bc8d5-7d32-429a-80e1-2e2d32cf0e14": "\"/providers/microsoft.powerapps/apis/shared_office365/connections/fe29ff7ed03344fdba6700dd1e27b745\"",
    "a55f400e-d891-4f8f-b32d-4df06d328f89": "\"/providers/microsoft.powerapps/apis/shared_sharepointonline/connections/6f7d00afdad3465c84bdd12b49f23331\"",
    "bf84baff-6f4c-4c1f-bd23-9ab7c11d374f": "\"/providers/microsoft.powerapps/apis/shared_sharepointonline/connections/1bb9748304ba489e84ad3970a53a3afa\"",
    "f31a593b-f385-4786-97a0-836f3962e255": "\"/providers/microsoft.powerapps/apis/shared_sharepointonline/connections/1bb9748304ba489e84ad3970a53a3afa\""
  },
  "LocalDatabaseReferencesAsEmpty": false,
  "LocalResourceFileNames": {
    "02_10_2023_08_05_06": "5e738668-690f-4bfa-a676-17a015cbfe67.jpg",
    "Design sem nome (3)": "85644337-6442-45f0-b967-7e936c95c93c.png",
    "Design_sem_nome__3_-removebg-preview": "8d4e3fec-77e7-4502-bf3d-915054916b7a.png",
    "Design_sem_nome__5_-removebg-preview": "3fdef7a7-fd6d-47bb-bddc-7c7284c4035b.png",
    "download": "0001.png",
    "Imagem não encontrada": "0002.png",
    "Logo Tooling - vetor": "0003.svg",
    "MicrosoftTeams-image (1)": "0004.png",
    "MicrosoftTeams-image (2)": "0005.png",
    "MicrosoftTeams-image (4)": "102eaeee-e1ad-4f4f-90aa-c2a913ad07b1.png",
    "MicrosoftTeams-image (5)": "0006.png",
    "MicrosoftTeams-image (6)": "0007.png",
    "MicrosoftTeams-image__5_-removebg-preview": "1efb4c5f-3e92-43d1-848a-7df3ace010a0.png",
    "nouveau_logo_renault_banner": "0009.jpg",
    "nouveau_logo_renault_banner-removebg-preview": "0008.png",
    "Renault Branca": "0010.png",
    "Renault Preta": "0011.png",
    "Renault-Logo": "0013.png",
    "renault-logo-evolution-removebg-preview": "0012.png"
  },
  "LocalResourceRootPaths": {
    "02_10_2023_08_05_06": "https://docserverpwaprodweu.blob.core.windows.net/c8f2b6d5-67cc-4bb3-8694-b8599db0ad0c-1/resource/Assets0Images05e738668-690f-4bfa-a676-17a015cbfe67.jpg?skoid=58690ece-ec83-4ce2-9ce8-883d4d6a54ee&sktid=975f013f-7f24-47e8-a7d3-abc4752bf346&skt=2023-10-02T14%3A36%3A00Z&ske=2023-10-03T14%3A51%3A00Z&sks=b&skv=2021-08-06&sv=2021-08-06&spr=https&se=2023-10-03T14%3A51%3A00Z&sr=b&sp=r&sig=8kwnIrbacHztN6G0MYaxBZ%2F5F1%2BrN%2FjrmNyYteYk6dk%3D",
    "Design sem nome (3)": "https://docserverpwaprodweu.blob.core.windows.net/c8f2b6d5-67cc-4bb3-8694-b8599db0ad0c-1/resource/Assets0Images085644337-6442-45f0-b967-7e936c95c93c.png?skoid=58690ece-ec83-4ce2-9ce8-883d4d6a54ee&sktid=975f013f-7f24-47e8-a7d3-abc4752bf346&skt=2023-10-02T14%3A36%3A00Z&ske=2023-10-03T14%3A51%3A00Z&sks=b&skv=2021-08-06&sv=2021-08-06&spr=https&se=2023-10-03T14%3A51%3A00Z&sr=b&sp=r&sig=Oxid7NSSVD3Sx4rPtVj8JdzCGRd%2Bc3Df2vaEIrk3kxY%3D",
    "Design_sem_nome__3_-removebg-preview": "https://docserverpwaprodweu.blob.core.windows.net/c8f2b6d5-67cc-4bb3-8694-b8599db0ad0c-1/resource/Assets0Images08d4e3fec-77e7-4502-bf3d-915054916b7a.png?skoid=58690ece-ec83-4ce2-9ce8-883d4d6a54ee&sktid=975f013f-7f24-47e8-a7d3-abc4752bf346&skt=2023-10-02T14%3A36%3A00Z&ske=2023-10-03T14%3A51%3A00Z&sks=b&skv=2021-08-06&sv=2021-08-06&spr=https&se=2023-10-03T14%3A51%3A00Z&sr=b&sp=r&sig=HQQ05I9p2OnJ7Aai%2FOqb5b5RFIwfpgEp0JePQgtMYas%3D",
    "Design_sem_nome__5_-removebg-preview": "https://docserverpwaprodweu.blob.core.windows.net/c8f2b6d5-67cc-4bb3-8694-b8599db0ad0c-1/resource/afd2680f-5476-4f0f-93bf-fa21936c3d33.png?skoid=58690ece-ec83-4ce2-9ce8-883d4d6a54ee&sktid=975f013f-7f24-47e8-a7d3-abc4752bf346&skt=2023-10-02T14%3A48%3A43Z&ske=2023-10-03T15%3A03%3A43Z&sks=b&skv=2021-08-06&sv=2021-08-06&spr=https&se=2023-10-03T15%3A03%3A43Z&sr=b&sp=r&sig=ro1arx9paJ3Aa7EVHZrbpilUznxlI3BdahpLe4Qi11U%3D",
    "download": "https://docserverpwaprodweu.blob.core.windows.net/c8f2b6d5-67cc-4bb3-8694-b8599db0ad0c-1/resource/Assets0Images00001.png?skoid=58690ece-ec83-4ce2-9ce8-883d4d6a54ee&sktid=975f013f-7f24-47e8-a7d3-abc4752bf346&skt=2023-10-02T14%3A36%3A00Z&ske=2023-10-03T14%3A51%3A00Z&sks=b&skv=2021-08-06&sv=2021-08-06&spr=https&se=2023-10-03T14%3A51%3A00Z&sr=b&sp=r&sig=SlRQFvZ9cGX19NXU6kPliBVFj2a9clvHIiMozV3kzwU%3D",
    "Imagem não encontrada": "https://docserverpwaprodweu.blob.core.windows.net/c8f2b6d5-67cc-4bb3-8694-b8599db0ad0c-1/resource/Assets0Images00002.png?skoid=58690ece-ec83-4ce2-9ce8-883d4d6a54ee&sktid=975f013f-7f24-47e8-a7d3-abc4752bf346&skt=2023-10-02T14%3A36%3A00Z&ske=2023-10-03T14%3A51%3A00Z&sks=b&skv=2021-08-06&sv=2021-08-06&spr=https&se=2023-10-03T14%3A51%3A00Z&sr=b&sp=r&sig=8hLbvpr67Jo67BadMhTlmRVuCDLv2ki4GIQ1fhxwFW8%3D",
    "Logo Tooling - vetor": "https://docserverpwaprodweu.blob.core.windows.net/c8f2b6d5-67cc-4bb3-8694-b8599db0ad0c-1/resource/Assets0Images00003.svg?skoid=58690ece-ec83-4ce2-9ce8-883d4d6a54ee&sktid=975f013f-7f24-47e8-a7d3-abc4752bf346&skt=2023-10-02T14%3A36%3A00Z&ske=2023-10-03T14%3A51%3A00Z&sks=b&skv=2021-08-06&sv=2021-08-06&spr=https&se=2023-10-03T14%3A51%3A00Z&sr=b&sp=r&sig=PqTjgQKNot6tXxCoeg8O0x%2BZGq4jRWUv3%2BimsxHtYRw%3D",
    "MicrosoftTeams-image (1)": "https://docserverpwaprodweu.blob.core.windows.net/c8f2b6d5-67cc-4bb3-8694-b8599db0ad0c-1/resource/Assets0Images00004.png?skoid=58690ece-ec83-4ce2-9ce8-883d4d6a54ee&sktid=975f013f-7f24-47e8-a7d3-abc4752bf346&skt=2023-10-02T14%3A36%3A00Z&ske=2023-10-03T14%3A51%3A00Z&sks=b&skv=2021-08-06&sv=2021-08-06&spr=https&se=2023-10-03T14%3A51%3A00Z&sr=b&sp=r&sig=yJ%2F%2Bf1DkOncoOHm4lEspFFhojdaZHgoXJnCHoiXokhM%3D",
    "MicrosoftTeams-image (2)": "https://docserverpwaprodweu.blob.core.windows.net/c8f2b6d5-67cc-4bb3-8694-b8599db0ad0c-1/resource/Assets0Images00005.png?skoid=58690ece-ec83-4ce2-9ce8-883d4d6a54ee&sktid=975f013f-7f24-47e8-a7d3-abc4752bf346&skt=2023-10-02T14%3A36%3A00Z&ske=2023-10-03T14%3A51%3A00Z&sks=b&skv=2021-08-06&sv=2021-08-06&spr=https&se=2023-10-03T14%3A51%3A00Z&sr=b&sp=r&sig=9%2FLGybVgFD4Cil5kDUTObyS%2Fkcj2MOKGCo8GlhGhqkA%3D",
    "MicrosoftTeams-image (4)": "https://docserverpwaprodweu.blob.core.windows.net/c8f2b6d5-67cc-4bb3-8694-b8599db0ad0c-1/resource/Assets0Images0102eaeee-e1ad-4f4f-90aa-c2a913ad07b1.png?skoid=58690ece-ec83-4ce2-9ce8-883d4d6a54ee&sktid=975f013f-7f24-47e8-a7d3-abc4752bf346&skt=2023-10-02T14%3A36%3A00Z&ske=2023-10-03T14%3A51%3A00Z&sks=b&skv=2021-08-06&sv=2021-08-06&spr=https&se=2023-10-03T14%3A51%3A00Z&sr=b&sp=r&sig=l7qar3PjPft5hwyaZYiScB4EgOXET4znuW5HCGavQsM%3D",
    "MicrosoftTeams-image (5)": "https://docserverpwaprodweu.blob.core.windows.net/c8f2b6d5-67cc-4bb3-8694-b8599db0ad0c-1/resource/Assets0Images00006.png?skoid=58690ece-ec83-4ce2-9ce8-883d4d6a54ee&sktid=975f013f-7f24-47e8-a7d3-abc4752bf346&skt=2023-10-02T14%3A36%3A00Z&ske=2023-10-03T14%3A51%3A00Z&sks=b&skv=2021-08-06&sv=2021-08-06&spr=https&se=2023-10-03T14%3A51%3A00Z&sr=b&sp=r&sig=1gA1q82rPTtIBwFyMbE0u2RGur06s%2F02qf1KO2n79w8%3D",
    "MicrosoftTeams-image (6)": "https://docserverpwaprodweu.blob.core.windows.net/c8f2b6d5-67cc-4bb3-8694-b8599db0ad0c-1/resource/Assets0Images00007.png?skoid=58690ece-ec83-4ce2-9ce8-883d4d6a54ee&sktid=975f013f-7f24-47e8-a7d3-abc4752bf346&skt=2023-10-02T14%3A36%3A00Z&ske=2023-10-03T14%3A51%3A00Z&sks=b&skv=2021-08-06&sv=2021-08-06&spr=https&se=2023-10-03T14%3A51%3A00Z&sr=b&sp=r&sig=fq8gACMvuQVSIU04PTKC1k0JST1YgdqvYO58izdMoqs%3D",
    "MicrosoftTeams-image__5_-removebg-preview": "https://docserverpwaprodweu.blob.core.windows.net/c8f2b6d5-67cc-4bb3-8694-b8599db0ad0c-1/resource/Assets0Images01efb4c5f-3e92-43d1-848a-7df3ace010a0.png?skoid=58690ece-ec83-4ce2-9ce8-883d4d6a54ee&sktid=975f013f-7f24-47e8-a7d3-abc4752bf346&skt=2023-10-02T14%3A36%3A00Z&ske=2023-10-03T14%3A51%3A00Z&sks=b&skv=2021-08-06&sv=2021-08-06&spr=https&se=2023-10-03T14%3A51%3A00Z&sr=b&sp=r&sig=FaXc5qw5KXliYhojK5GHMlptr5ZtuRH40yfWEgqCXKc%3D",
    "nouveau_logo_renault_banner": "https://docserverpwaprodweu.blob.core.windows.net/c8f2b6d5-67cc-4bb3-8694-b8599db0ad0c-1/resource/Assets0Images00009.jpg?skoid=58690ece-ec83-4ce2-9ce8-883d4d6a54ee&sktid=975f013f-7f24-47e8-a7d3-abc4752bf346&skt=2023-10-02T14%3A36%3A00Z&ske=2023-10-03T14%3A51%3A00Z&sks=b&skv=2021-08-06&sv=2021-08-06&spr=https&se=2023-10-03T14%3A51%3A00Z&sr=b&sp=r&sig=n1WdPOpwdjPoZzk3JUguxLuyW53Phiq1DHGJbWVgXJk%3D",
    "nouveau_logo_renault_banner-removebg-preview": "https://docserverpwaprodweu.blob.core.windows.net/c8f2b6d5-67cc-4bb3-8694-b8599db0ad0c-1/resource/Assets0Images00008.png?skoid=58690ece-ec83-4ce2-9ce8-883d4d6a54ee&sktid=975f013f-7f24-47e8-a7d3-abc4752bf346&skt=2023-10-02T14%3A36%3A00Z&ske=2023-10-03T14%3A51%3A00Z&sks=b&skv=2021-08-06&sv=2021-08-06&spr=https&se=2023-10-03T14%3A51%3A00Z&sr=b&sp=r&sig=br1qb0J20LA3CtL4%2F%2F2cjDZQK8kVxYaYXHsOBzI0LkU%3D",
    "Renault Branca": "https://docserverpwaprodweu.blob.core.windows.net/c8f2b6d5-67cc-4bb3-8694-b8599db0ad0c-1/resource/Assets0Images00010.png?skoid=58690ece-ec83-4ce2-9ce8-883d4d6a54ee&sktid=975f013f-7f24-47e8-a7d3-abc4752bf346&skt=2023-10-02T14%3A36%3A00Z&ske=2023-10-03T14%3A51%3A00Z&sks=b&skv=2021-08-06&sv=2021-08-06&spr=https&se=2023-10-03T14%3A51%3A00Z&sr=b&sp=r&sig=mNt3chhBXZAYwOjTjJ%2BQOyLgN%2FXlDGq8mjBfWk9QeWM%3D",
    "Renault Preta": "https://docserverpwaprodweu.blob.core.windows.net/c8f2b6d5-67cc-4bb3-8694-b8599db0ad0c-1/resource/Assets0Images00011.png?skoid=58690ece-ec83-4ce2-9ce8-883d4d6a54ee&sktid=975f013f-7f24-47e8-a7d3-abc4752bf346&skt=2023-10-02T14%3A36%3A00Z&ske=2023-10-03T14%3A51%3A00Z&sks=b&skv=2021-08-06&sv=2021-08-06&spr=https&se=2023-10-03T14%3A51%3A00Z&sr=b&sp=r&sig=DnBoZijdDKQES3p1vgiKUvWjrPTg3rjM7l8LJA6tfeo%3D",
    "Renault-Logo": "https://docserverpwaprodweu.blob.core.windows.net/c8f2b6d5-67cc-4bb3-8694-b8599db0ad0c-1/resource/Assets0Images00013.png?skoid=58690ece-ec83-4ce2-9ce8-883d4d6a54ee&sktid=975f013f-7f24-47e8-a7d3-abc4752bf346&skt=2023-10-02T14%3A36%3A00Z&ske=2023-10-03T14%3A51%3A00Z&sks=b&skv=2021-08-06&sv=2021-08-06&spr=https&se=2023-10-03T14%3A51%3A00Z&sr=b&sp=r&sig=EYht8GVPlHRTsknvZj7LV1OGLTOYq1BS%2BnDMDH2GIwQ%3D",
    "renault-logo-evolution-removebg-preview": "https://docserverpwaprodweu.blob.core.windows.net/c8f2b6d5-67cc-4bb3-8694-b8599db0ad0c-1/resource/Assets0Images00012.png?skoid=58690ece-ec83-4ce2-9ce8-883d4d6a54ee&sktid=975f013f-7f24-47e8-a7d3-abc4752bf346&skt=2023-10-02T14%3A36%3A00Z&ske=2023-10-03T14%3A51%3A00Z&sks=b&skv=2021-08-06&sv=2021-08-06&spr=https&se=2023-10-03T14%3A51%3A00Z&sr=b&sp=r&sig=oDp4nvtjeDMzDoTEu4euQ8FN2zVsuMTMQehXAfX6b%2FQ%3D"
  },
  "OldLogoFileName": "4yqjm5pt.jpg",
  "OrderComponentMetadata": {},
  "OrderComponentTemplate": {},
  "OrderDataSource": {
    "ComboBoxSample": 1,
    "CONTROLEDEMATERIAIS3D": 6,
    "CustomGallerySample": 2,
    "DropDownSample": 3,
    "Estoque 3D": 4,
    "Office365Outlook": 0,
    "RadioSample": 5
  },
  "OrderGroupControls": {
    "Aumentar fonte": {
      "Fontes_3": 0,
      "Slider1": 1
    },
    "Group1": {
      "AddArquivo": 2,
      "AddMediaButton1": 3,
      "TextInput3": 1,
      "TextInput3_1": 0
    },
    "Group10": {
      "Icon4": 0,
      "Label3_5": 1
    },
    "Group11": {
      "Icon7": 0,
      "Label3": 1
    },
    "Group12": {
      "Filtro_1": 3,
      "Gallery2": 0,
      "Icon3_2": 2,
      "Icon3_3": 5,
      "Icon6_1": 4,
      "TextSearchBox1_1": 1
    },
    "Group2": {
      "Label4": 0,
      "Label4_1": 1
    },
    "Group3": {
      "color_amarelo": 3,
      "color_branco": 1,
      "color_preto": 2,
      "Cores": 0
    },
    "Group4": {
      "Icon7_2": 0,
      "Label3_3": 1
    },
    "Group5": {
      "Icon5": 0,
      "Timer2": 1
    },
    "Group6": {
      "Filtro_2": 3,
      "Gallery2_1": 0,
      "Icon3": 2,
      "Icon3_1": 4,
      "Icon6": 5,
      "TextSearchBox1_2": 1
    },
    "Group8": {
      "Icon1": 0,
      "Label3_2": 1
    },
    "Group9": {
      "Icon7_1": 0,
      "Label3_1": 1
    }
  },
  "OrderPcfTemplate": {},
  "OrderTemplate": {},
  "OrderXMLTemplate": {
    "addMedia": 7,
    "button": 5,
    "combobox": 2,
    "datepicker": 8,
    "form": 0,
    "gallery": 14,
    "groupContainer": 9,
    "icon": 4,
    "image": 6,
    "label": 1,
    "radio": 13,
    "rectangle": 10,
    "slider": 11,
    "text": 3,
    "timer": 12
  },
  "OverridablePropertiesEntry": {
    "Acessivel": {},
    "AddArquivo": {},
    "AddMediaButton1": {},
    "AddPicture1": {},
    "AddPicture2": {},
    "ajuda": {},
    "Ajuda": {},
    "Ajuda_1": {},
    "Anexo_DataCard1": {},
    "Anexo_DataCard2": {},
    "App": {},
    "Aumentar fonte": {},
    "Body3": {},
    "Body3_1": {},
    "Button2": {},
    "color_amarelo": {},
    "color_branco": {},
    "color_preto": {},
    "Configuracao": {},
    "Container1": {},
    "Container1_1": {},
    "Cor_DataCard1": {},
    "Cor_DataCard2": {},
    "Cor_DataCard3": {},
    "Cores": {},
    "Data_DataCard1": {},
    "Data_DataCard2": {},
    "DataCardKey1": {},
    "DataCardKey10": {},
    "DataCardKey11": {},
    "DataCardKey12": {},
    "DataCardKey13": {},
    "DataCardKey14": {},
    "DataCardKey15": {},
    "DataCardKey16": {},
    "DataCardKey17": {},
    "DataCardKey18": {},
    "DataCardKey19": {},
    "DataCardKey2": {},
    "DataCardKey20": {},
    "DataCardKey21": {},
    "DataCardKey22": {},
    "DataCardKey23": {},
    "DataCardKey24": {},
    "DataCardKey25": {},
    "DataCardKey26": {},
    "DataCardKey27": {},
    "DataCardKey28": {},
    "DataCardKey29": {},
    "DataCardKey3": {},
    "DataCardKey4": {},
    "DataCardKey6": {},
    "DataCardKey7": {},
    "DataCardKey8": {},
    "DataCardKey9": {},
    "DataCardValue1": {},
    "DataCardValue10": {},
    "DataCardValue11": {},
    "DataCardValue12": {},
    "DataCardValue13": {},
    "DataCardValue14": {},
    "DataCardValue15": {},
    "DataCardValue16": {},
    "DataCardValue17": {},
    "DataCardValue18": {},
    "DataCardValue19": {},
    "DataCardValue2": {},
    "DataCardValue20": {},
    "DataCardValue21": {},
    "DataCardValue22": {},
    "DataCardValue23": {},
    "DataCardValue24": {},
    "DataCardValue25": {},
    "DataCardValue26": {},
    "DataCardValue27": {},
    "DataCardValue3": {},
    "DataCardValue5": {},
    "DataCardValue6": {},
    "DataCardValue7": {},
    "DataCardValue8": {},
    "DataCardValue9": {},
    "Diâmetro_DataCard2": {},
    "Diâmetro_DataCard3": {},
    "Diâmetro_DataCard4": {},
    "ErrorMessage1": {},
    "ErrorMessage10": {},
    "ErrorMessage11": {},
    "ErrorMessage12": {},
    "ErrorMessage13": {},
    "ErrorMessage14": {},
    "ErrorMessage15": {},
    "ErrorMessage16": {},
    "ErrorMessage17": {},
    "ErrorMessage18": {},
    "ErrorMessage19": {},
    "ErrorMessage2": {},
    "ErrorMessage20": {},
    "ErrorMessage21": {},
    "ErrorMessage22": {},
    "ErrorMessage23": {},
    "ErrorMessage24": {},
    "ErrorMessage25": {},
    "ErrorMessage26": {},
    "ErrorMessage27": {},
    "ErrorMessage28": {},
    "ErrorMessage3": {},
    "ErrorMessage4": {},
    "ErrorMessage5": {},
    "ErrorMessage6": {},
    "ErrorMessage7": {},
    "ErrorMessage8": {},
    "ErrorMessage9": {},
    "Fabricante_DataCard1": {},
    "Fabricante_DataCard2": {},
    "Fabricante_DataCard3": {},
    "Fechar": {},
    "Filtro_1": {},
    "Filtro_2": {},
    "Fontes": {},
    "Fontes_1": {},
    "Fontes_2": {},
    "Fontes_3": {},
    "Fontes_4": {},
    "Form1": {},
    "Form2": {},
    "Form3": {},
    "Gallery2": {},
    "Gallery2_1": {},
    "galleryTemplate3": {},
    "galleryTemplate3_1": {},
    "Group1": {},
    "Group10": {},
    "Group11": {},
    "Group12": {},
    "Group2": {},
    "Group3": {},
    "Group4": {},
    "Group5": {},
    "Group6": {},
    "Group8": {},
    "Group9": {},
    "Host": {},
    "Icon1": {},
    "Icon3": {},
    "Icon3_1": {},
    "Icon3_2": {},
    "Icon3_3": {},
    "Icon4": {},
    "Icon5": {},
    "Icon5_1": {},
    "Icon6": {},
    "Icon6_1": {},
    "Icon7": {},
    "Icon7_1": {},
    "Icon7_2": {},
    "Icon7_3": {},
    "Icon7_4": {},
    "Image1": {},
    "Image3": {},
    "Image5": {},
    "Label1": {},
    "Label2_2": {},
    "Label3": {},
    "Label3_1": {},
    "Label3_2": {},
    "Label3_3": {},
    "Label3_4": {},
    "Label3_5": {},
    "Label3_6": {},
    "Label4": {},
    "Label4_1": {},
    "Localização_DataCard1": {},
    "Localização_DataCard2": {},
    "Localização_DataCard3": {},
    "localizar": {},
    "Localizar 2": {},
    "Localizar Button": {},
    "login": {},
    "Logo estoque": {},
    "Logo Estoque": {},
    "Logo estoque_1": {},
    "Logo Estoque_1": {},
    "Logo Estoque_2": {},
    "Logo Estoque_3": {},
    "Material_DataCard1": {},
    "Material_DataCard2": {},
    "Material_DataCard3": {},
    "Material_DataCard4": {},
    "movimentacao": {},
    "Movimentacao Button": {},
    "Movimentacao Button_1": {},
    "movimentacao2": {},
    "NextArrow5": {},
    "NextArrow5_1": {},
    "Nome_DataCard1": {},
    "Nome_DataCard3": {},
    "PopUp_acessibilidade": {},
    "principal": {},
    "Quant._DataCard1": {},
    "Quant._DataCard2": {},
    "Quant._DataCard3": {},
    "Radio1_2": {},
    "Radio1_3": {},
    "Radio1_4": {},
    "Radio1_5": {},
    "Separator5_1": {},
    "Separator5_2": {},
    "Slider1": {},
    "StarVisible1": {},
    "StarVisible10": {},
    "StarVisible11": {},
    "StarVisible12": {},
    "StarVisible13": {},
    "StarVisible14": {},
    "StarVisible15": {},
    "StarVisible16": {},
    "StarVisible17": {},
    "StarVisible18": {},
    "StarVisible19": {},
    "StarVisible2": {},
    "StarVisible20": {},
    "StarVisible21": {},
    "StarVisible22": {},
    "StarVisible23": {},
    "StarVisible24": {},
    "StarVisible25": {},
    "StarVisible26": {},
    "StarVisible27": {},
    "StarVisible28": {},
    "StarVisible3": {},
    "StarVisible4": {},
    "StarVisible5": {},
    "StarVisible6": {},
    "StarVisible7": {},
    "StarVisible8": {},
    "StarVisible9": {},
    "Status_DataCard1": {},
    "Status_DataCard2": {},
    "Subtitle5": {},
    "Subtitle5_1": {},
    "TextInput1": {},
    "TextInput2": {},
    "TextInput3": {},
    "TextInput3_1": {},
    "TextSearchBox1_1": {},
    "TextSearchBox1_2": {},
    "Timer2": {},
    "Title5": {},
    "Title5_1": {},
    "Título_DataCard1": {},
    "Tooling Logo": {},
    "Tooling Logo_1": {},
    "Tooling Logo_2": {},
    "Tooling Logo_4": {},
    "UploadedImage1": {}
  },
  "PCFDynamicSchemaForIRRetrievalEntry": {},
  "PCFTemplateEntry": {},
  "PublishOrderIndices": {
    "Acessivel": 5,
    "AddArquivo": 39,
    "AddMediaButton1": 40,
    "AddPicture1": 240,
    "AddPicture2": 131,
    "ajuda": 1,
    "Ajuda": 31,
    "Ajuda_1": 41,
    "Anexo_DataCard1": 236,
    "Anexo_DataCard2": 127,
    "App": 0,
    "Aumentar fonte": 16,
    "Body3": 117,
    "Body3_1": 61,
    "Button2": 3,
    "color_amarelo": 9,
    "color_branco": 10,
    "color_preto": 11,
    "Configuracao": 30,
    "Container1": 46,
    "Container1_1": 102,
    "Cor_DataCard1": 221,
    "Cor_DataCard2": 133,
    "Cor_DataCard3": 73,
    "Cores": 7,
    "Data_DataCard1": 138,
    "Data_DataCard2": 206,
    "DataCardKey1": 129,
    "DataCardKey10": 193,
    "DataCardKey11": 140,
    "DataCardKey12": 145,
    "DataCardKey13": 188,
    "DataCardKey14": 213,
    "DataCardKey15": 233,
    "DataCardKey16": 150,
    "DataCardKey17": 155,
    "DataCardKey18": 203,
    "DataCardKey19": 198,
    "DataCardKey2": 223,
    "DataCardKey20": 160,
    "DataCardKey21": 165,
    "DataCardKey22": 170,
    "DataCardKey23": 175,
    "DataCardKey24": 95,
    "DataCardKey25": 180,
    "DataCardKey26": 208,
    "DataCardKey27": 85,
    "DataCardKey28": 90,
    "DataCardKey29": 228,
    "DataCardKey3": 218,
    "DataCardKey4": 238,
    "DataCardKey6": 80,
    "DataCardKey7": 135,
    "DataCardKey8": 70,
    "DataCardKey9": 75,
    "DataCardValue1": 136,
    "DataCardValue10": 146,
    "DataCardValue11": 189,
    "DataCardValue12": 214,
    "DataCardValue13": 234,
    "DataCardValue14": 151,
    "DataCardValue15": 156,
    "DataCardValue16": 204,
    "DataCardValue17": 199,
    "DataCardValue18": 161,
    "DataCardValue19": 166,
    "DataCardValue2": 224,
    "DataCardValue20": 171,
    "DataCardValue21": 176,
    "DataCardValue22": 96,
    "DataCardValue23": 181,
    "DataCardValue24": 209,
    "DataCardValue25": 86,
    "DataCardValue26": 91,
    "DataCardValue27": 229,
    "DataCardValue3": 219,
    "DataCardValue5": 81,
    "DataCardValue6": 71,
    "DataCardValue7": 76,
    "DataCardValue8": 141,
    "DataCardValue9": 194,
    "Diâmetro_DataCard2": 78,
    "Diâmetro_DataCard3": 143,
    "Diâmetro_DataCard4": 226,
    "ErrorMessage1": 132,
    "ErrorMessage10": 195,
    "ErrorMessage11": 72,
    "ErrorMessage12": 77,
    "ErrorMessage13": 190,
    "ErrorMessage14": 87,
    "ErrorMessage15": 235,
    "ErrorMessage16": 147,
    "ErrorMessage17": 152,
    "ErrorMessage18": 205,
    "ErrorMessage19": 200,
    "ErrorMessage2": 225,
    "ErrorMessage20": 157,
    "ErrorMessage21": 92,
    "ErrorMessage22": 162,
    "ErrorMessage23": 167,
    "ErrorMessage24": 172,
    "ErrorMessage25": 177,
    "ErrorMessage26": 182,
    "ErrorMessage27": 210,
    "ErrorMessage28": 230,
    "ErrorMessage3": 220,
    "ErrorMessage4": 241,
    "ErrorMessage5": 215,
    "ErrorMessage6": 137,
    "ErrorMessage7": 82,
    "ErrorMessage8": 97,
    "ErrorMessage9": 142,
    "Fabricante_DataCard1": 178,
    "Fabricante_DataCard2": 231,
    "Fabricante_DataCard3": 93,
    "Fechar": 22,
    "Filtro_1": 106,
    "Filtro_2": 50,
    "Fontes": 12,
    "Fontes_1": 19,
    "Fontes_2": 20,
    "Fontes_3": 15,
    "Fontes_4": 21,
    "Form1": 185,
    "Form2": 67,
    "Form3": 126,
    "Gallery2": 112,
    "Gallery2_1": 56,
    "galleryTemplate3": 113,
    "galleryTemplate3_1": 57,
    "Group1": 37,
    "Group10": 120,
    "Group11": 121,
    "Group12": 105,
    "Group2": 14,
    "Group3": 8,
    "Group4": 65,
    "Group5": 23,
    "Group6": 49,
    "Group8": 183,
    "Group9": 184,
    "Host": 0,
    "Icon1": 245,
    "Icon3": 54,
    "Icon3_1": 55,
    "Icon3_2": 109,
    "Icon3_3": 111,
    "Icon4": 124,
    "Icon5": 24,
    "Icon5_1": 32,
    "Icon6": 53,
    "Icon6_1": 110,
    "Icon7": 123,
    "Icon7_1": 244,
    "Icon7_2": 64,
    "Icon7_3": 98,
    "Icon7_4": 43,
    "Image1": 130,
    "Image3": 239,
    "Image5": 0,
    "Label1": 25,
    "Label2_2": 125,
    "Label3": 122,
    "Label3_1": 243,
    "Label3_2": 242,
    "Label3_3": 66,
    "Label3_4": 99,
    "Label3_5": 119,
    "Label3_6": 44,
    "Label4": 18,
    "Label4_1": 13,
    "Localização_DataCard1": 196,
    "Localização_DataCard2": 88,
    "Localização_DataCard3": 153,
    "localizar": 50,
    "Localizar 2": 15,
    "Localizar Button": 28,
    "login": 73,
    "Logo estoque": 27,
    "Logo Estoque": 101,
    "Logo estoque_1": 34,
    "Logo Estoque_1": 45,
    "Logo Estoque_2": 47,
    "Logo Estoque_3": 103,
    "Material_DataCard1": 216,
    "Material_DataCard2": 186,
    "Material_DataCard3": 148,
    "Material_DataCard4": 68,
    "movimentacao": 79,
    "Movimentacao Button": 29,
    "Movimentacao Button_1": 100,
    "movimentacao2": 105,
    "NextArrow5": 115,
    "NextArrow5_1": 59,
    "Nome_DataCard1": 158,
    "Nome_DataCard3": 211,
    "PopUp_acessibilidade": 6,
    "principal": 160,
    "Quant._DataCard1": 83,
    "Quant._DataCard2": 201,
    "Quant._DataCard3": 163,
    "Radio1_2": 107,
    "Radio1_3": 108,
    "Radio1_4": 51,
    "Radio1_5": 52,
    "Separator5_1": 62,
    "Separator5_2": 118,
    "Slider1": 17,
    "StarVisible1": 128,
    "StarVisible10": 192,
    "StarVisible11": 69,
    "StarVisible12": 74,
    "StarVisible13": 187,
    "StarVisible14": 84,
    "StarVisible15": 232,
    "StarVisible16": 144,
    "StarVisible17": 149,
    "StarVisible18": 202,
    "StarVisible19": 197,
    "StarVisible2": 222,
    "StarVisible20": 154,
    "StarVisible21": 89,
    "StarVisible22": 159,
    "StarVisible23": 164,
    "StarVisible24": 169,
    "StarVisible25": 174,
    "StarVisible26": 179,
    "StarVisible27": 207,
    "StarVisible28": 227,
    "StarVisible3": 217,
    "StarVisible4": 237,
    "StarVisible5": 212,
    "StarVisible6": 134,
    "StarVisible7": 79,
    "StarVisible8": 94,
    "StarVisible9": 139,
    "Status_DataCard1": 168,
    "Status_DataCard2": 191,
    "Subtitle5": 116,
    "Subtitle5_1": 60,
    "TextInput1": 2,
    "TextInput2": 1,
    "TextInput3": 38,
    "TextInput3_1": 36,
    "TextSearchBox1_1": 104,
    "TextSearchBox1_2": 48,
    "Timer2": 26,
    "Title5": 114,
    "Title5_1": 58,
    "Título_DataCard1": 173,
    "Tooling Logo": 33,
    "Tooling Logo_1": 4,
    "Tooling Logo_2": 63,
    "Tooling Logo_4": 42,
    "UploadedImage1": 35
  },
  "ResourcesJsonIndices": {
    "Image-02_10_2023_08_05_06": 15,
    "Image-Design sem nome (3)": 17,
    "Image-Design_sem_nome__3_-removebg-preview": 18,
    "Image-Design_sem_nome__5_-removebg-preview": 19,
    "Image-download": 1,
    "Image-Imagem não encontrada": 2,
    "Image-Logo Tooling - vetor": 3,
    "Image-MicrosoftTeams-image (1)": 4,
    "Image-MicrosoftTeams-image (2)": 5,
    "Image-MicrosoftTeams-image (4)": 14,
    "Image-MicrosoftTeams-image (5)": 6,
    "Image-MicrosoftTeams-image (6)": 7,
    "Image-MicrosoftTeams-image__5_-removebg-preview": 16,
    "Image-nouveau_logo_renault_banner": 9,
    "Image-nouveau_logo_renault_banner-removebg-preview": 8,
    "Image-Renault Branca": 10,
    "Image-Renault Preta": 11,
    "Image-Renault-Logo": 13,
    "Image-renault-logo-evolution-removebg-preview": 12,
    "Image-SampleImage": 0
  },
  "RuleScreenIdWithoutScreen": {},
  "TemplateVersions": {},
  "VolatileProperties": {
    "AnalysisLoadTime": 1.570764,
    "ControlCount": {
      "addMedia": 3,
      "button": 17,
      "combobox": 13,
      "datepicker": 2,
      "form": 3,
      "gallery": 2,
      "galleryTemplate": 2,
      "group": 12,
      "groupContainer": 5,
      "icon": 18,
      "image": 14,
      "label": 101,
      "radio": 4,
      "rectangle": 3,
      "screen": 7,
      "slider": 1,
      "text": 17,
      "timer": 1,
      "typedDataCard": 28
    },
    "DeserializationLoadTime": 3.0410301
  },
  "WasLocalDatabaseReferencesEmpty": true
}